{"type":"FeatureCollection","features":[{"geometry":{"type":"Polygon","coordinates":[[[9.334,0.000],[9.137,-0.573],[8.821,-0.708],[8.703,-0.591],[9.065,-1.298],[9.347,-1.325],[9.296,-1.515],[9.523,-1.598],[9.319,-1.632],[9.036,-1.309],[9.266,-1.825],[9.495,-1.935],[9.299,-1.903],[9.676,-2.416],[10.062,-2.550],[9.722,-2.468],[11.778,-4.566],[12.315,-5.895],[12.515,-6.004],[13.068,-5.865],[12.283,-6.124],[12.823,-6.955],[13.379,-8.370],[13.359,-8.687],[12.999,-9.048],[13.834,-10.930],[13.785,-11.813],[13.598,-12.286],[12.983,-12.776],[12.550,-13.438],[12.016,-15.514],[11.751,-15.832],[11.733,-17.751],[14.118,-21.943],[0.000,-21.943],[0.000,0.000],[9.334,0.000]]]},"type":"Feature","id":"632c7b9cfd","clipped":true,"properties":{"source":"naturalearthdata.com","kind":"ocean","name":"","area":470012248366126}},{"geometry":{"type":"LineString","coordinates":[[0.000,0.000],[0.000,-21.943]]},"type":"Feature","id":"168485e191","clipped":true,"properties":{"source":"naturalearthdata.com","kind":"ocean","name":"","area":574532018975187}},{"geometry":{"type":"Polygon","coordinates":[[[16.859,-18.813],[16.091,-19.070],[15.891,-18.968],[15.920,-18.754],[16.608,-18.529],[16.859,-18.813]]]},"type":"Feature","id":"45d2e72de2","clipped":true,"properties":{"source":"naturalearthdata.com","kind":"playa","name":"Etosha Pan","area":3811300183}},{"geometry":{"type":"Polygon","coordinates":[[[18.036,-0.957],[17.901,-0.736],[17.811,-0.672],[18.114,-0.708],[18.129,-0.981],[18.036,-0.957]]]},"type":"Feature","id":"0d42fadd51","clipped":true,"properties":{"source":"naturalearthdata.com","kind":"lake","name":"Lac Tumba","area":715390456}}]}