{"type":"FeatureCollection","features":[{"geometry":{"type":"LineString","coordinates":[[0.000,-61.606],[0.000,-55.777]]},"type":"Feature","id":"632c7b9cfd","clipped":true,"properties":{"source":"naturalearthdata.com","kind":"ocean","name":"","area":470012248366126}},{"geometry":{"type":"Polygon","coordinates":[[[0.000,-55.777],[0.000,-61.606],[-11.250,-61.606],[-11.250,-55.777],[0.000,-55.777]]]},"type":"Feature","id":"168485e191","clipped":true,"properties":{"source":"naturalearthdata.com","kind":"ocean","name":"","area":574532018975187}}]}