{"type":"FeatureCollection","features":[{"geometry":{"type":"MultiPolygon","coordinates":[[[[40.319,40.980],[40.128,40.943],[39.825,40.980],[40.319,40.980]]],[[[38.715,40.980],[38.381,40.925],[38.044,40.980],[38.715,40.980]]],[[[33.750,36.206],[34.023,36.341],[34.300,36.604],[34.704,36.817],[35.393,36.575],[35.537,36.597],[35.661,36.724],[36.049,36.911],[36.180,36.807],[36.188,36.659],[35.811,36.310],[35.957,35.998],[35.840,35.849],[35.764,35.572],[35.902,35.421],[35.943,35.224],[35.888,34.949],[35.978,34.547],[35.648,34.248],[35.612,34.032],[35.109,33.084],[34.702,31.952],[33.750,31.952],[33.750,34.973],[34.050,34.988],[33.908,35.202],[33.942,35.292],[34.556,35.662],[33.750,35.392],[33.750,36.206]]]]},"type":"Feature","id":"632c7b9cfd","clipped":true,"properties":{"source":"naturalearthdata.com","kind":"ocean","name":"","area":470012248366126}},{"geometry":{"type":"Polygon","coordinates":[[[43.595,33.306],[43.483,33.190],[43.309,33.349],[43.382,33.435],[43.595,33.306]]]},"type":"Feature","id":"b3fff0e9da","clipped":true,"properties":{"source":"naturalearthdata.com","kind":"lake","name":"Lake Habbaniyah","area":559971075}},{"geometry":{"type":"Polygon","coordinates":[[[44.990,40.515],[44.972,40.542],[45.000,40.613],[45.000,40.510],[44.990,40.515]]]},"type":"Feature","id":"39ce05f335","clipped":true,"properties":{"source":"naturalearthdata.com","kind":"lake","name":"Lake Sevana","area":2329639527}},{"geometry":{"type":"Polygon","coordinates":[[[43.261,33.728],[43.106,33.915],[43.066,34.258],[43.116,34.329],[43.493,33.888],[43.478,33.729],[43.261,33.728]]]},"type":"Feature","id":"1afe1d1c26","clipped":true,"properties":{"source":"naturalearthdata.com","kind":"lake","name":"Lake Tharthar","area":2147911231}},{"geometry":{"type":"Polygon","coordinates":[[[42.989,38.346],[42.856,38.484],[42.353,38.500],[42.458,38.692],[42.526,38.745],[43.079,38.809],[43.163,38.846],[43.075,38.916],[43.152,38.948],[43.560,38.978],[43.611,38.947],[43.292,38.813],[43.210,38.716],[43.186,38.603],[43.318,38.489],[43.148,38.337],[42.989,38.346]]]},"type":"Feature","id":"7585c0e8dc","clipped":true,"properties":{"source":"naturalearthdata.com","kind":"lake","name":"Lake Van","area":5608420854}},{"geometry":{"type":"Polygon","coordinates":[[[43.878,32.688],[43.793,32.535],[43.482,32.642],[43.423,32.810],[43.508,33.060],[43.550,33.079],[43.720,32.808],[43.878,32.688]]]},"type":"Feature","id":"7a511e4452","clipped":true,"properties":{"source":"naturalearthdata.com","kind":"lake","name":"Razzaza Lake (Lake Milh)","area":1990451696}},{"geometry":{"type":"Polygon","coordinates":[[[35.632,32.782],[35.577,32.720],[35.565,32.892],[35.623,32.878],[35.632,32.782]]]},"type":"Feature","id":"9ea0228e57","clipped":true,"properties":{"source":"naturalearthdata.com","kind":"lake","name":"Sea of Galilee","area":196015797}}]}